README
setup.py
smithery/__init__.py
smithery.recipe.smiths.egg-info/PKG-INFO
smithery.recipe.smiths.egg-info/SOURCES.txt
smithery.recipe.smiths.egg-info/dependency_links.txt
smithery.recipe.smiths.egg-info/entry_points.txt
smithery.recipe.smiths.egg-info/namespace_packages.txt
smithery.recipe.smiths.egg-info/not-zip-safe
smithery.recipe.smiths.egg-info/requires.txt
smithery.recipe.smiths.egg-info/top_level.txt
smithery/recipe/__init__.py
smithery/recipe/smiths/__init__.py
smithery/recipe/smiths/base.py
smithery/recipe/smiths/xpath.py
smithery/recipe/smiths/tests/__init__.py
smithery/recipe/smiths/tests/test_docs.py